sphinx_godot_theme/__init__.py
sphinx_godot_theme/robots.txt
sphinx_godot_theme/static/css/custom.css
sphinx_godot_theme/static/js/custom.js
sphinx_godot_theme/templates/layout.html
sphinx_godot_theme-0.4.2.dist-info/LICENSE
sphinx_godot_theme-0.4.2.dist-info/WHEEL
sphinx_godot_theme-0.4.2.dist-info/METADATA
sphinx_godot_theme-0.4.2.dist-info/RECORD
